README.md
setup.cfg
setup.py
Topsis/__init__.py
Topsis/__main__.py
Topsis_Pratyush_102103302.egg-info/PKG-INFO
Topsis_Pratyush_102103302.egg-info/SOURCES.txt
Topsis_Pratyush_102103302.egg-info/dependency_links.txt
Topsis_Pratyush_102103302.egg-info/entry_points.txt
Topsis_Pratyush_102103302.egg-info/requires.txt
Topsis_Pratyush_102103302.egg-info/top_level.txt