Metadata-Version: 2.1
Name: Topsis-Pratyush-102103302
Version: 1.0.0
Summary: Done by Pratyush Saxena
Home-page: UNKNOWN
Author: Pratyush Saxena
Author-email: psaxena_be21@thapar.edu
License: MIT
Platform: UNKNOWN
Classifier: License :: OSI Approved :: MIT License
Classifier: Programming Language :: Python :: 3.6
Classifier: Programming Language :: Python :: 3.7
Classifier: Programming Language :: Python :: 3.8
